dependeless/__init__.py
dependeless/main.py
dependeless-0.1.1.dist-info/entry_points.txt
dependeless-0.1.1.dist-info/LICENSE
dependeless-0.1.1.dist-info/WHEEL
dependeless-0.1.1.dist-info/METADATA
dependeless-0.1.1.dist-info/RECORD
