Metadata-Version: 2.1
Name: dependeless
Version: 0.1.1
Summary: A tool to show which pip packages are not depended on by any other package
Keywords: pip,dependencies,unused,packages,clean
Author-email: Lucas van der Horst <Lucas@vdrHorst.nl>
Requires-Python: >=3.10
Classifier: Development Status :: 3 - Alpha
Classifier: Intended Audience :: Developers
Classifier: Topic :: Software Development :: Build Tools
Classifier: License :: OSI Approved :: GNU General Public License v3 (GPLv3)
Classifier: Programming Language :: Python :: 3
Classifier: Programming Language :: Python :: 3.10
Requires-Dist: click>=8.1
Requires-Dist: pip3-autoremove>=1.2
Project-URL: Bug Tracker, https://gitlab.com/Lucas_van_der_Horst/dependeless/-/issues
Project-URL: Documentation, https://gitlab.com/Lucas_van_der_Horst/dependeless/-/blob/main/README.md
Project-URL: Homepage, https://gitlab.com/Lucas_van_der_Horst/dependeless
Project-URL: Source Code, https://gitlab.com/Lucas_van_der_Horst/dependeless
